{"entities": [{"name": "dlq_total", "type": "CONCEPT", "context": "Counter for total number of dead-letter queue messages"}, {"name": "dlq_replayed_total", "type": "CONCEPT", "context": "Counter for total number of messages replayed from the dead-letter queue"}, {"name": "visibility_extensions_total", "type": "CONCEPT", "context": "Counter for total number of visibility extensions"}, {"name": "Log Contract", "type": "CONCEPT", "context": "Specification for structured JSON logs"}], "relationships": []}