{"entities": [{"name": "Ayush", "type": "PERSON", "context": "Collaborator with product background, first-time working on operations/GTM with V"}, {"name": "Operations/GTM work", "type": "CONCEPT", "context": "Type of work V and Ayush are collaborating on for the first time"}, {"name": "Market dynamics", "type": "CONCEPT", "context": "Area where Ayush will provide future value once onboarded"}, {"name": "Product background", "type": "CONCEPT", "context": "Ayush's professional background and expertise area"}], "relationships": [{"from": "V", "to": "Ayush", "type": "WORKS_WITH", "context": "First-time collaboration on operations/GTM work; relationship is solid with mutual commitment"}, {"from": "Ayush", "to": "Product background", "type": "USES", "context": "His professional background that will provide future value"}, {"from": "Ayush", "to": "Market dynamics", "type": "RELATED_TO", "context": "Needs onboarding on market dynamics to leverage product background"}, {"from": "Ayush", "to": "Operations/GTM work", "type": "RELATED_TO", "context": "First-time working in this area"}]}