{"entities": [{"name": "Ilya", "type": "PERSON", "context": "Finalizing employer-facing marketing videos for Careerspan"}, {"name": "Technical-focused marketing approach", "type": "CONCEPT", "context": "Video script introducing technology and problem-solving capabilities"}, {"name": "Buyer-centric marketing approach", "type": "CONCEPT", "context": "Video script focused on empowering HR professionals"}], "relationships": [{"from": "Ilya", "to": "Technical-focused marketing approach", "type": "USES", "context": "Creating technical-focused employer marketing video"}, {"from": "Ilya", "to": "Buyer-centric marketing approach", "type": "USES", "context": "Creating buyer-centric employer marketing video"}, {"from": "Technical-focused marketing approach", "to": "Buyer-centric marketing approach", "type": "RELATED_TO", "context": "Two complementary approaches to employer-facing marketing"}]}