{"entities": [{"name": "@Nyne", "type": "TOOL", "context": "Used for researching specific people or companies."}, {"name": "@CRM Profile Enrichment", "type": "TOOL", "context": "Trigger for enriching CRM profiles."}, {"name": "@CRM Org Enrichment", "type": "TOOL", "context": "Trigger for enriching CRM organizations."}, {"name": "get_recent_social_activity", "type": "TOOL", "context": "Function used to populate social presence sections."}, {"name": "python3", "type": "TOOL", "context": "Programming language used to run test suite."}, {"name": "Integrations/Nyne/test_suite.py", "type": "TOOL", "context": "Script used to verify API connectivity and credit balance."}], "relationships": []}