{"entities": [{"name": "Vrijen Attawar", "type": "PERSON", "context": "Speaker discussing funding credits"}, {"name": "Google", "type": "ORG", "context": "Provides funding credits for startups"}, {"name": "pre seed funding", "type": "CONCEPT", "context": "Initial stage of funding for startups"}, {"name": "seed funding", "type": "CONCEPT", "context": "Second stage of funding for startups"}, {"name": "credits", "type": "TOOL", "context": "Currency for funding support"}, {"name": "startup", "type": "CONCEPT", "context": "Business venture being funded"}], "relationships": [{"from": "Vrijen Attawar", "to": "Google", "type": "MENTIONS", "context": "Discusses Google's funding support"}, {"from": "Vrijen Attawar", "to": "pre seed funding", "type": "BELIEVES", "context": "References importance in funding process"}, {"from": "Vrijen Attawar", "to": "seed funding", "type": "BELIEVES", "context": "References importance in funding process"}, {"from": "Google", "to": "pre seed funding", "type": "USES", "context": "Provides credits"}, {"from": "Google", "to": "seed funding", "type": "USES", "context": "Provides credits"}]}