{"entities": [{"name": "Iron Triangle", "type": "CONCEPT", "context": "Triangulation method for human truth in hiring assessment using three disparate contexts"}, {"name": "Self-reflection", "type": "CONCEPT", "context": "One plane of assessment, prone to blind spots bias"}, {"name": "Interview performance", "type": "CONCEPT", "context": "One plane of assessment, prone to performance/charm bias"}, {"name": "External validation", "type": "CONCEPT", "context": "One plane of assessment, prone to networking bias"}, {"name": "Narrative drift", "type": "CONCEPT", "context": "Inconsistency between the three assessment planes that indicates potential false narrative"}, {"name": "Ground truth", "type": "CONCEPT", "context": "Reliable truth indicated by consistency across all three assessment planes"}, {"name": "Careerspan assessment engine", "type": "TOOL", "context": "System to be designed to detect narrative drift across assessment planes"}, {"name": "Careerspan", "type": "ORG", "context": "V's company building the assessment engine"}], "relationships": [{"from": "Iron Triangle", "to": "Self-reflection", "type": "RELATED_TO", "context": "Self-reflection is one of the three planes in the Iron Triangle"}, {"from": "Iron Triangle", "to": "Interview performance", "type": "RELATED_TO", "context": "Interview performance is one of the three planes in the Iron Triangle"}, {"from": "Iron Triangle", "to": "External validation", "type": "RELATED_TO", "context": "External validation is one of the three planes in the Iron Triangle"}, {"from": "Iron Triangle", "to": "Ground truth", "type": "RELATED_TO", "context": "Consistency across Iron Triangle planes indicates ground truth"}, {"from": "Careerspan assessment engine", "to": "Iron Triangle", "type": "USES", "context": "Engine must implement triangulation across three planes"}, {"from": "Careerspan assessment engine", "to": "Narrative drift", "type": "USES", "context": "Engine must detect narrative drift to flag inconsistent candidates"}, {"from": "Careerspan", "to": "Careerspan assessment engine", "type": "RELATED_TO", "context": "Careerspan is building this assessment tool"}]}