{"entities": [{"name": "Zo", "type": "PERSON", "context": "entity initiating actions"}, {"name": "Howie", "type": "PERSON", "context": "entity receiving actions"}, {"name": "Person", "type": "PERSON", "context": "generic person referenced in relationship warming suggestions"}, {"name": "Meeting", "type": "CONCEPT", "context": "generic meeting referenced in notifications"}, {"name": "Topic", "type": "CONCEPT", "context": "generic topic referenced in follow-up recommendations"}], "relationships": [{"from": "Zo", "to": "Howie", "type": "WORKS_WITH", "context": "Zo initiates actions to assist Howie"}, {"from": "Howie", "to": "Person", "type": "KNOWS", "context": "Howie interacts with various persons"}, {"from": "Howie", "to": "Meeting", "type": "RELATED_TO", "context": "Howie receives notifications about meetings"}, {"from": "Howie", "to": "Topic", "type": "RELATED_TO", "context": "Howie receives follow-up recommendations about topics"}]}