{"entities": [{"name": "V", "type": "PERSON", "context": "refers to the individual involved in the knowledge system"}, {"name": "Akiflow", "type": "TOOL", "context": "a task management tool used to manage actions"}, {"name": "Aki", "type": "PERSON", "context": "the individual associated with the email interface"}], "relationships": [{"from": "V", "to": "Akiflow", "type": "USES", "context": "V uses Akiflow to manage tasks"}, {"from": "Aki", "to": "Akiflow", "type": "WORKS_WITH", "context": "Aki is associated with Akiflow's email interface"}]}