{"entities": [{"name": "Tesla", "type": "ORG", "context": "current company where V is employed"}, {"name": "California State Polytechnic University-Pomona", "type": "ORG", "context": "latest educational institution attended by V"}, {"name": "Marketing/ Brand and Product Management/ Sales Management", "type": "CONCEPT", "context": "field of study of V"}], "relationships": [{"from": "V", "to": "Tesla", "type": "WORKS_WITH", "context": "current employment at Tesla"}, {"from": "V", "to": "California State Polytechnic University-Pomona", "type": "KNOWS", "context": "attended university for education"}]}