{"entities": [{"name": "V (Vrijen)", "type": "PERSON", "context": "Individual associated with the knowledge system"}, {"name": "Careerspan", "type": "ORG", "context": "Organization related to placement success"}, {"name": "employment transitions", "type": "CONCEPT", "context": "Concept relating to status changes in employment"}], "relationships": [{"from": "V (Vrijen)", "to": "Careerspan", "type": "USES", "context": "V uses Careerspan to measure placement success"}, {"from": "employment transitions", "to": "Careerspan", "type": "RELATED_TO", "context": "Employment transitions are measured by Careerspan"}]}