{"entities": [{"name": "Ilya", "type": "PERSON", "context": "Team member who raised the question about formalizing the pipeline and used the 'buffet line' analogy"}, {"name": "Logan", "type": "PERSON", "context": "Team member who emphasizes consistent noise-making as core to creating partnership conversations"}, {"name": "V", "type": "PERSON", "context": "Vrijen Attawar, founder of Careerspan, advocating a relationship-first partnership approach with Superposition"}, {"name": "Superposition", "type": "ORG", "context": "Potential partner org; V advocates sending founders first before formalizing the relationship"}, {"name": "Teal", "type": "ORG", "context": "Company whose CEO was reached via a TikTok, cited by Logan as an example of noise creating traction"}, {"name": "Pipedrive", "type": "TOOL", "context": "CRM/pipeline tool; team chose to delay heavy setup until opportunity volume justifies it"}, {"name": "Process Should Scale With Volume", "type": "CONCEPT", "context": "Principle that tooling and process should follow real opportunity volume, not precede it"}, {"name": "Relationship-First Partnership", "type": "CONCEPT", "context": "V's approach: demonstrate value by sending founders first, then formalize once traction is evident"}, {"name": "Consistent Noise Strategy", "type": "CONCEPT", "context": "Logan's emphasis that persistent visibility (e.g. TikTok content) creates partnership opportunities"}, {"name": "GTM Strategy", "type": "CONCEPT", "context": "Go-to-market context in which these strategic decisions and partnership framing are situated"}, {"name": "TikTok", "type": "TOOL", "context": "Content platform used to reach Teal's CEO, illustrating the consistent noise strategy"}], "relationships": [{"from": "Ilya", "to": "Process Should Scale With Volume", "type": "BELIEVES", "context": "Ilya articulated the principle using the 'buffet line / peanut bowl' analogy"}, {"from": "V", "to": "Relationship-First Partnership", "type": "BELIEVES", "context": "V advocates sending founders first and formalizing partnerships only after demonstrated traction"}, {"from": "V", "to": "Superposition", "type": "RELATED_TO", "context": "V is shaping the partnership framing \u2014 lead with value, not money"}, {"from": "Logan", "to": "Consistent Noise Strategy", "type": "BELIEVES", "context": "Logan emphasizes that persistent noise (content, outreach) is core to generating partnership conversations"}, {"from": "Consistent Noise Strategy", "to": "TikTok", "type": "USES", "context": "TikTok content that reached Teal's CEO is the cited example of the noise strategy working"}, {"from": "TikTok", "to": "Teal", "type": "RELATED_TO", "context": "A TikTok video reached Teal's CEO, creating a partnership conversation opportunity"}, {"from": "Process Should Scale With Volume", "to": "Pipedrive", "type": "RELATED_TO", "context": "The team decided to delay heavy Pipedrive setup based on this scaling principle"}, {"from": "Relationship-First Partnership", "to": "GTM Strategy", "type": "RELATED_TO", "context": "The partnership framing is a component of broader go-to-market planning"}, {"from": "Consistent Noise Strategy", "to": "GTM Strategy", "type": "RELATED_TO", "context": "Noise-making is positioned as core to the GTM and partnership development approach"}, {"from": "Ilya", "to": "V", "type": "WORKS_WITH", "context": "Ilya and V collaborate on pipeline and process decisions"}, {"from": "Logan", "to": "V", "type": "WORKS_WITH", "context": "Logan and V collaborate on GTM strategy and partnership development"}]}