{"entities": [{"name": "Jaya", "type": "PERSON", "context": "Has ventures that may potentially align with Careerspan; peer advisor relationship with V"}, {"name": "Careerspan", "type": "ORG", "context": "V's company; potential for future collaboration if aligned with Jaya's ventures"}], "relationships": [{"from": "V", "to": "Jaya", "type": "RELATED_TO", "context": "Peer advisor relationship; informal ongoing connection"}, {"from": "Careerspan", "to": "Jaya", "type": "RELATED_TO", "context": "Potential future collaboration if product trajectories align"}]}