{"entities": [{"name": "V", "type": "PERSON", "context": "individual involved in the knowledge system"}, {"name": "Game Design for CTFs", "type": "CONCEPT", "context": "concept related to designing Capture The Flag games"}, {"name": "ARG narrative scaffolding", "type": "CONCEPT", "context": "concept related to designing alternate reality games"}], "relationships": [{"from": "V", "to": "Game Design for CTFs", "type": "KNOWS", "context": "V has knowledge about this concept"}, {"from": "V", "to": "ARG narrative scaffolding", "type": "KNOWS", "context": "V has knowledge about this concept"}]}