{"entities": [{"name": "execute_with_safety", "type": "CONCEPT", "context": "a function for executing commands with safety checks"}, {"name": "command_spec", "type": "CONCEPT", "context": "specifications for commands including permissions and side effects"}, {"name": "args", "type": "CONCEPT", "context": "arguments passed to the execute function"}, {"name": "execute_function", "type": "CONCEPT", "context": "function to execute the command"}, {"name": "os", "type": "TOOL", "context": "module used for accessing operating system functionalities"}, {"name": "Error", "type": "BELIEF", "context": "exception type used for error handling"}], "relationships": [{"from": "execute_with_safety", "to": "command_spec", "type": "USES", "context": "uses command specifications to perform safety checks"}, {"from": "execute_with_safety", "to": "args", "type": "USES", "context": "uses arguments for execution control"}, {"from": "execute_with_safety", "to": "execute_function", "type": "USES", "context": "calls the execute function to perform the command"}, {"from": "execute_with_safety", "to": "os", "type": "USES", "context": "uses the os module to check environment variables"}, {"from": "execute_with_safety", "to": "Error", "type": "MENTIONS", "context": "mentions the Error type for exception handling"}]}