{"entities": [{"name": "Rules", "type": "TOOL", "context": "System feature for setting persistent preferences that persist across sessions"}, {"name": "Lists", "type": "TOOL", "context": "Reusable knowledge storage that can be queried and extended"}, {"name": "planning prompt", "type": "TOOL", "context": "Prompt loaded before significant building work"}, {"name": "tools list", "type": "TOOL", "context": "A list containing tool information that can be queried"}], "relationships": [{"from": "Rules", "to": "planning prompt", "type": "USES", "context": "Rules can trigger loading the planning prompt before building work"}, {"from": "Lists", "to": "tools list", "type": "RELATED_TO", "context": "The tools list is an instance of the Lists system"}]}