{"entities": [{"name": "V (Vrijen)", "type": "PERSON", "context": "individual associated with the knowledge system"}, {"name": "Columbia", "type": "ORG", "context": "partner organization"}, {"name": "UMass", "type": "ORG", "context": "partner organization"}, {"name": "HBS", "type": "ORG", "context": "organization in the partnership pipeline"}, {"name": "Cornell", "type": "ORG", "context": "organization in the partnership pipeline"}], "relationships": [{"from": "V (Vrijen)", "to": "Columbia", "type": "WORKS_WITH", "context": "live partnership"}, {"from": "V (Vrijen)", "to": "UMass", "type": "WORKS_WITH", "context": "live partnership"}, {"from": "V (Vrijen)", "to": "HBS", "type": "RELATED_TO", "context": "pipeline for future partnership"}, {"from": "V (Vrijen)", "to": "Cornell", "type": "RELATED_TO", "context": "pipeline for future partnership"}]}