{"entities": [{"name": "Builder persona", "type": "CONCEPT", "context": "a defined role within the knowledge system"}, {"name": "Strategist persona", "type": "CONCEPT", "context": "a defined role within the knowledge system"}, {"name": "Teacher persona", "type": "CONCEPT", "context": "a defined role within the knowledge system"}, {"name": "P36/P37 decision matrix", "type": "TOOL", "context": "a functionality within the system"}, {"name": "System navigation", "type": "CONCEPT", "context": "related to how the knowledge system is organized"}, {"name": "directory structure", "type": "CONCEPT", "context": "related to how the knowledge system is organized"}], "relationships": [{"from": "V", "to": "Builder persona", "type": "WORKS_WITH", "context": "integration of the builder persona"}, {"from": "V", "to": "Strategist persona", "type": "WORKS_WITH", "context": "integration of the strategist persona"}, {"from": "V", "to": "Teacher persona", "type": "WORKS_WITH", "context": "development of the teaching framework"}, {"from": "V", "to": "P36/P37 decision matrix", "type": "USES", "context": "functionality to aid in decision making"}, {"from": "V", "to": "System navigation", "type": "USES", "context": "to navigate the knowledge system"}, {"from": "V", "to": "directory structure", "type": "USES", "context": "to organize the knowledge system"}]}