{"entities": [{"name": "Logan", "type": "PERSON", "context": "Team member at Careerspan, handles campaigns and logos"}, {"name": "Vrijen", "type": "PERSON", "context": "Founder of Careerspan, leading partnership conversations"}, {"name": "Ilse", "type": "PERSON", "context": "Team member at Careerspan, handles demos and product exploration"}, {"name": "Edmund", "type": "PERSON", "context": "Co-founder of Superposition, philosophically opposed to marketplaces"}, {"name": "Superposition", "type": "ORG", "context": "Technical recruiting firm building employer-side analog of Careerspan"}, {"name": "Careerspan", "type": "ORG", "context": "V's company, candidate-focused recruiting platform"}, {"name": "Getro", "type": "TOOL", "context": "Platform Ilse will explore for GTM experiments"}, {"name": "Blue Sapphire demo account", "type": "TOOL", "context": "Demo environment for Careerspan product demonstrations"}, {"name": "Quality of candidates over quantity", "type": "CONCEPT", "context": "Guiding principle - all product roads should lead back to this"}, {"name": "Revenue-sharing model", "type": "CONCEPT", "context": "Partnership pricing approach with fee for rent of the link plus smaller share"}, {"name": "Superposition Partnership Call", "type": "EVENT", "context": "Upcoming call to discuss Careerspan-Superposition partnership"}], "relationships": [{"from": "Vrijen", "to": "Careerspan", "type": "WORKS_WITH", "context": "Founder of Careerspan"}, {"from": "Logan", "to": "Careerspan", "type": "WORKS_WITH", "context": "Team member handling campaigns and branding"}, {"from": "Ilse", "to": "Careerspan", "type": "WORKS_WITH", "context": "Team member handling demos and product exploration"}, {"from": "Edmund", "to": "Superposition", "type": "WORKS_WITH", "context": "Co-founder of Superposition"}, {"from": "Superposition", "to": "Careerspan", "type": "RELATED_TO", "context": "Building employer-side analog, potential anchor partner"}, {"from": "Edmund", "to": "Careerspan", "type": "USES", "context": "Willing to use Careerspan for candidates via partnership"}, {"from": "Careerspan", "to": "Quality of candidates over quantity", "type": "BELIEVES", "context": "Core product principle team shares"}, {"from": "Vrijen", "to": "Revenue-sharing model", "type": "USES", "context": "Considering for Superposition partnership pricing"}, {"from": "Ilse", "to": "Blue Sapphire demo account", "type": "USES", "context": "Will reuse for Superposition demo"}, {"from": "Ilse", "to": "Getro", "type": "USES", "context": "Will explore as GTM experiment"}]}