{"entities": [{"name": "Ilya", "type": "PERSON", "context": "Team member responsible for video scripts, audio versions, and visual mockups for marketing initiative"}, {"name": "Vrijen", "type": "PERSON", "context": "Owner/leader handling Superposition AI partnership initiative"}, {"name": "Superposition AI", "type": "ORG", "context": "Company being pursued for partnership with flat-rate-per-link proposal"}, {"name": "B40", "type": "CONCEPT", "context": "Parent initiative block containing Superposition partnership and marketing video development"}, {"name": "B40.T2", "type": "CONCEPT", "context": "Marketing video development initiative within B40"}, {"name": "Flat-rate-per-link proposal", "type": "CONCEPT", "context": "Partnership pricing model being finalized with Superposition AI"}, {"name": "Call with Superposition AI", "type": "EVENT", "context": "Upcoming partnership call to be scheduled by Vrijen"}], "relationships": [{"from": "Ilya", "to": "Vrijen", "type": "WORKS_WITH", "context": "Team coordination on marketing video deliverables"}, {"from": "Vrijen", "to": "Superposition AI", "type": "WORKS_WITH", "context": "Setting up partnership and finalizing terms"}, {"from": "B40.T2", "to": "B40", "type": "RELATED_TO", "context": "Marketing video development is a sub-initiative of B40"}, {"from": "Flat-rate-per-link proposal", "to": "Superposition AI", "type": "RELATED_TO", "context": "Partnership pricing model for Superposition deal"}, {"from": "Call with Superposition AI", "to": "Superposition AI", "type": "RELATED_TO", "context": "Initial partnership discussion meeting"}]}