{"entities": [{"name": "V", "type": "PERSON", "context": "individual associated with the knowledge system"}, {"name": "incantum triggers", "type": "TOOL", "context": "a feature or tool used within the knowledge system"}, {"name": "schemas", "type": "CONCEPT", "context": "structural elements identified in the knowledge system"}, {"name": "Knowledge", "type": "CONCEPT", "context": "a category within the knowledge system"}, {"name": "Lists", "type": "CONCEPT", "context": "a category within the knowledge system"}, {"name": "Records", "type": "CONCEPT", "context": "a category within the knowledge system"}, {"name": "N5", "type": "CONCEPT", "context": "a specific structure within the knowledge system"}, {"name": "Careerspan", "type": "CONCEPT", "context": "a category or component of the knowledge system"}, {"name": "Meetings", "type": "CONCEPT", "context": "a category related to interactions within the knowledge system"}, {"name": "Personal", "type": "CONCEPT", "context": "a category concerning personal interactions within the knowledge system"}], "relationships": []}