{"entities": [{"name": "Vrijen", "type": "PERSON", "context": "associated with the knowledge system"}, {"name": "Context Boundaries", "type": "CONCEPT", "context": "principle related to knowledge patterns"}, {"name": "Rule-of-Two", "type": "CONCEPT", "context": "a previous guideline now updated to a new principle"}, {"name": "minimal context principle", "type": "CONCEPT", "context": "current guiding principle in the knowledge system"}, {"name": "P8", "type": "BELIEF", "context": "new reference to the principle of minimal context"}, {"name": "P0", "type": "BELIEF", "context": "previous reference to the Rule-of-Two"}], "relationships": [{"from": "Vrijen", "to": "Context Boundaries", "type": "KNOWS", "context": "V is familiar with this concept in the knowledge system"}, {"from": "Vrijen", "to": "Rule-of-Two", "type": "MENTIONS", "context": "V references this outdated guideline"}, {"from": "Vrijen", "to": "minimal context principle", "type": "BELIEVES", "context": "V adopts this as the current principle"}, {"from": "Rule-of-Two", "to": "minimal context principle", "type": "RELATED_TO", "context": "Rule-of-Two is the previous name for this guiding principle"}]}