{"entities": [{"name": "Resume", "type": "CONCEPT", "context": "Artifact questioned as having diminishing signal value, compared to business card"}, {"name": "Business card", "type": "CONCEPT", "context": "Historical artifact that persists for tradition despite low signal value"}, {"name": "Signal value", "type": "CONCEPT", "context": "The information/insight content an artifact carries for decision-making"}, {"name": "GitHub", "type": "TOOL", "context": "Platform that can surface deeper candidate insights than traditional resume"}, {"name": "Portfolios", "type": "TOOL", "context": "Alternative to resumes for demonstrating candidate capabilities"}, {"name": "AI-powered candidate summaries", "type": "TOOL", "context": "Technology that can surface deeper insights faster than traditional resumes"}], "relationships": [{"from": "Resume", "to": "Business card", "type": "RELATED_TO", "context": "Provocation comparing resume's trajectory to business card's obsolescence"}, {"from": "GitHub", "to": "Resume", "type": "RELATED_TO", "context": "Positioned as higher-signal alternative to resumes"}, {"from": "Portfolios", "to": "Resume", "type": "RELATED_TO", "context": "Positioned as higher-signal alternative to resumes"}, {"from": "AI-powered candidate summaries", "to": "Resume", "type": "RELATED_TO", "context": "Positioned as faster path to deeper candidate insights"}]}