{"entities": [{"name": "V", "type": "PERSON", "context": "the subject of the knowledge system"}, {"name": "org_scanning_enabled", "type": "CONCEPT", "context": "a setting that controls scanning behavior"}, {"name": "talent pools", "type": "ORG", "context": "specific organizations related to candidate selection"}, {"name": "partner networks", "type": "ORG", "context": "another type of organization related to candidate selection"}], "relationships": [{"from": "V", "to": "org_scanning_enabled", "type": "KNOWS", "context": "V is aware of the scanning settings"}, {"from": "org_scanning_enabled", "to": "talent pools", "type": "RELATED_TO", "context": "scans are limited to members of organizations such as talent pools"}, {"from": "org_scanning_enabled", "to": "partner networks", "type": "RELATED_TO", "context": "scans are limited to members of organizations such as partner networks"}]}