{"entities": [{"name": "V (Vrijen)", "type": "PERSON", "context": "Founder of Dobzi"}, {"name": "Dobzi", "type": "ORG", "context": "Company founded by V (Vrijen)"}, {"name": "Uber", "type": "ORG", "context": "Company that V (Vrijen) signed"}, {"name": "HelloFresh", "type": "ORG", "context": "Company that V (Vrijen) signed"}, {"name": "mid-sized business owners/operators", "type": "CONCEPT", "context": "Target audience for V's ask"}], "relationships": [{"from": "V (Vrijen)", "to": "Dobzi", "type": "FOUNDED", "context": "V is the founder of Dobzi"}, {"from": "V (Vrijen)", "to": "Uber", "type": "SIGNED", "context": "V signed a contract with Uber"}, {"from": "V (Vrijen)", "to": "HelloFresh", "type": "SIGNED", "context": "V signed a contract with HelloFresh"}, {"from": "V (Vrijen)", "to": "mid-sized business owners/operators", "type": "ASKS_FOR_INTRODUCTIONS", "context": "V is seeking introductions to this group"}]}