{"entities": [{"name": "Careerspan", "type": "ORG", "context": "V's company, positioned as a high-quality candidate pipeline that integrates into employer-side workflows"}, {"name": "General-Purpose Marketplaces", "type": "CONCEPT", "context": "A model V is philosophically opposed to; prefers specialization over broad platforms"}, {"name": "Structured Collaboration", "type": "CONCEPT", "context": "V's preferred model where each side specializes and meets via deliberate coordination rather than open marketplace dynamics"}, {"name": "Employer-Side Workflows", "type": "CONCEPT", "context": "The workflows on the hiring/employer side that Careerspan's pipeline is designed to slot into"}, {"name": "High-Quality Candidate Pipeline", "type": "CONCEPT", "context": "How Careerspan is framed as a value proposition \u2014 curated quality over marketplace volume"}, {"name": "Fee-for-Link-Rent Model", "type": "CONCEPT", "context": "A simple commercial construct where a fee is charged for access/link rental, paired with a modest success-based component"}, {"name": "Success-Based Component", "type": "CONCEPT", "context": "A modest performance-based fee layer that rewards Careerspan without conflicting with V's preferred commercial model"}], "relationships": [{"from": "Vrijen", "to": "General-Purpose Marketplaces", "type": "BELIEVES", "context": "Philosophically opposed; views them as inferior to specialized, structured collaboration"}, {"from": "Vrijen", "to": "Structured Collaboration", "type": "BELIEVES", "context": "Prefers each side to specialize and meet via structured collaboration rather than broad marketplaces"}, {"from": "Careerspan", "to": "High-Quality Candidate Pipeline", "type": "RELATED_TO", "context": "Careerspan is presented as the high-quality pipeline that feeds into employer workflows"}, {"from": "Careerspan", "to": "Employer-Side Workflows", "type": "RELATED_TO", "context": "Careerspan slots cleanly into employer-side workflows as a candidate source"}, {"from": "Fee-for-Link-Rent Model", "to": "Success-Based Component", "type": "RELATED_TO", "context": "Combined commercial construct: link rent fee plus modest success-based reward"}, {"from": "Vrijen", "to": "Fee-for-Link-Rent Model", "type": "USES", "context": "Preferred simple commercial construct that respects V's model while rewarding Careerspan"}, {"from": "Careerspan", "to": "Structured Collaboration", "type": "RELATED_TO", "context": "Careerspan embodies the structured-collaboration philosophy rather than marketplace dynamics"}]}