{"entities": [{"name": "Careerspan", "type": "ORG", "context": "Company name"}, {"name": "Apply AI", "type": "ORG", "context": "Legacy name of Careerspan"}, {"name": "mycareerspan.com", "type": "TOOL", "context": "Email domain"}, {"name": "theapply.ai", "type": "TOOL", "context": "Email domain"}, {"name": "Employee canonicalization", "type": "CONCEPT", "context": "Concept related to employee data"}], "relationships": [{"from": "V", "to": "Careerspan", "type": "WORKS_WITH", "context": "V is associated with the company"}, {"from": "V", "to": "Apply AI", "type": "WORKS_WITH", "context": "V is associated with the legacy name of the company"}, {"from": "V", "to": "mycareerspan.com", "type": "USES", "context": "V uses the internal email domain"}, {"from": "V", "to": "theapply.ai", "type": "USES", "context": "V uses the internal email domain"}, {"from": "V", "to": "Employee canonicalization", "type": "KNOWS", "context": "V is aware of the concept of employee canonicalization"}, {"from": "V", "to": "Downstream effects", "type": "MENTIONS", "context": "V references downstream effects related to scheduling, digests, CRM"}]}