{"entities": [{"name": "Ben Lang", "type": "PERSON", "context": "Owner of the Next Play Community"}, {"name": "Next Play Community", "type": "ORG", "context": "A community with a subscription model"}, {"name": "Vrijen", "type": "PERSON", "context": "Individual whose name is used as a referral"}], "relationships": [{"from": "Vrijen", "to": "Next Play Community", "type": "USES", "context": "Vrijen's name used as a referral for signing up"}, {"from": "Ben Lang", "to": "Next Play Community", "type": "WORKS_WITH", "context": "Owner of the community"}]}