{"entities": [{"name": "Jake Weissbourd", "type": "PERSON", "context": "FOHE representative who indicated a pilot probably makes sense"}, {"name": "Ray Batra", "type": "PERSON", "context": "FOHE representative who committed to scoping the pilot"}, {"name": "Logan", "type": "PERSON", "context": "Careerspan representative who will maintain momentum and share materials"}, {"name": "FOHE", "type": "ORG", "context": "Organization exploring a pilot partnership with Careerspan"}, {"name": "Careerspan", "type": "ORG", "context": "V's company offering product demo to FOHE"}, {"name": "Pilot", "type": "CONCEPT", "context": "Potential trial engagement between FOHE and Careerspan"}, {"name": "Email demo", "type": "EVENT", "context": "Pending product demonstration of additional Careerspan features"}], "relationships": [{"from": "Jake Weissbourd", "to": "FOHE", "type": "WORKS_WITH", "context": "Represents FOHE in partnership discussions"}, {"from": "Ray Batra", "to": "FOHE", "type": "WORKS_WITH", "context": "Represents FOHE and committed to scoping"}, {"from": "Logan", "to": "Careerspan", "type": "WORKS_WITH", "context": "Careerspan representative maintaining deal momentum"}, {"from": "FOHE", "to": "Pilot", "type": "RELATED_TO", "context": "Moving from exploration to execution on pilot"}, {"from": "Careerspan", "to": "FOHE", "type": "RELATED_TO", "context": "Potential pilot partnership being scoped"}, {"from": "Careerspan", "to": "Email demo", "type": "RELATED_TO", "context": "Willing to showcase product features to FOHE team"}]}