{"entities": [{"name": "Ash Straughn", "type": "PERSON", "context": "Speaker discussing partnerships"}, {"name": "Andrew Young", "type": "PERSON", "context": "Hosted a founders event"}, {"name": "career span", "type": "ORG", "context": "Company focused on job seeking"}, {"name": "talent unlocked", "type": "ORG", "context": "Platform for capturing talent information"}, {"name": "5% kickback", "type": "CONCEPT", "context": "Partnership payment structure"}], "relationships": [{"from": "Ash Straughn", "to": "Andrew Young", "type": "WORKS_WITH", "context": "Met at a founders event"}, {"from": "Ash Straughn", "to": "career span", "type": "MENTIONS", "context": "Discussing the platform and partnership"}, {"from": "Ash Straughn", "to": "talent unlocked", "type": "USES", "context": "Seeking partnership for talent access"}, {"from": "Ash Straughn", "to": "5% kickback", "type": "MENTIONS", "context": "Discussing payment structure in partnerships"}]}