{"entities": [{"name": "V (Vrijen)", "type": "PERSON", "context": "Content Creator and Podcast Host"}, {"name": "The Data Guy", "type": "ORG", "context": "V's brand for thought leadership"}, {"name": "#MakeCompassionCoolAgain", "type": "BELIEF", "context": "Value-driven belief in compassion and kindness"}, {"name": "metrics", "type": "CONCEPT", "context": "Focus on data-driven decision-making"}, {"name": "analytics", "type": "CONCEPT", "context": "Focus on data-driven decision-making"}, {"name": "evidence-based decision-making", "type": "CONCEPT", "context": "Focus on data-driven decision-making"}, {"name": "warm introductions", "type": "CONCEPT", "context": "Preference over cold outreach"}, {"name": "cold outreach", "type": "CONCEPT", "context": "Contrast to warm introductions"}, {"name": "deep work", "type": "CONCEPT", "context": "Discussed focus technique"}, {"name": "productivity", "type": "CONCEPT", "context": "Discussed focus technique"}, {"name": "focus techniques", "type": "CONCEPT", "context": "Discussed focus technique"}], "relationships": [{"from": "V (Vrijen)", "to": "The Data Guy", "type": "WORKS_WITH", "context": "V is the creator of The Data Guy brand"}, {"from": "V (Vrijen)", "to": "#MakeCompassionCoolAgain", "type": "BELIEVES", "context": "V believes in promoting compassion and kindness"}, {"from": "V (Vrijen)", "to": "metrics", "type": "USES", "context": "V focuses on metrics for decision-making"}, {"from": "V (Vrijen)", "to": "analytics", "type": "USES", "context": "V focuses on analytics for decision-making"}, {"from": "V (Vrijen)", "to": "evidence-based decision-making", "type": "USES", "context": "V emphasizes evidence in decision-making"}, {"from": "V (Vrijen)", "to": "warm introductions", "type": "MENTIONS", "context": "V prefers warm introductions over cold outreach"}, {"from": "V (Vrijen)", "to": "cold outreach", "type": "MENTIONS", "context": "V contrasts this with warm introductions"}, {"from": "V (Vrijen)", "to": "deep work", "type": "MENTIONS", "context": "V discusses deep work as a focus technique"}, {"from": "V (Vrijen)", "to": "productivity", "type": "MENTIONS", "context": "V discusses productivity in the context of focus techniques"}, {"from": "V (Vrijen)", "to": "focus techniques", "type": "MENTIONS", "context": "V discusses various methods for maintaining focus"}]}