{"entities": [{"name": "V", "type": "PERSON", "context": "individual reviewing extracted examples"}, {"name": "Gmail corpus", "type": "CONCEPT", "context": "source of extracted examples"}, {"name": "style guide", "type": "CONCEPT", "context": "document to include selected examples"}, {"name": "mycareerspan.com", "type": "ORG", "context": "organization linked to email source"}], "relationships": [{"from": "V", "to": "style guide", "type": "USES", "context": "V will select examples to include"}, {"from": "V", "to": "Gmail corpus", "type": "KNOWS", "context": "V is reviewing extracted examples from this corpus"}, {"from": "V", "to": "mycareerspan.com", "type": "WORKS_WITH", "context": "V's email is associated with this organization"}]}