{"entities": [{"name": "Strategic Partner", "type": "CONCEPT", "context": "Phase 1 of strategic thinking framework"}, {"name": "Reflection Synthesizer", "type": "CONCEPT", "context": "Phase 2 focused on structured outputs"}, {"name": "Weekly Review", "type": "CONCEPT", "context": "Phase 3 for long-term processing and reconciliation"}, {"name": "Weekly Strategic Review", "type": "CONCEPT", "context": "Process where strategic sessions become strategic clarity"}], "relationships": [{"from": "Strategic Partner", "to": "Reflection Synthesizer", "type": "RELATED_TO", "context": "Phase 1 feeds into Phase 2 in strategic framework"}, {"from": "Reflection Synthesizer", "to": "Weekly Review", "type": "RELATED_TO", "context": "Phase 2 feeds into Phase 3 for long-term resolution"}, {"from": "Weekly Strategic Review", "to": "Weekly Review", "type": "RELATED_TO", "context": "Weekly Strategic Review implements the Phase 3 Weekly Review concept"}]}