{"entities": [{"name": "NEA", "type": "ORG", "context": "V's key customer"}, {"name": "Republic Capital", "type": "ORG", "context": "V's key customer"}, {"name": "8VC", "type": "ORG", "context": "V's key customer"}, {"name": "Uber", "type": "ORG", "context": "V's key customer"}, {"name": "Aviato's data quality", "type": "CONCEPT", "context": "V's competitive positioning against PitchBook"}, {"name": "PitchBook", "type": "ORG", "context": "Competitor to V's knowledge system"}], "relationships": [{"from": "V", "to": "NEA", "type": "WORKS_WITH", "context": "Key customer of V"}, {"from": "V", "to": "Republic Capital", "type": "WORKS_WITH", "context": "Key customer of V"}, {"from": "V", "to": "8VC", "type": "WORKS_WITH", "context": "Key customer of V"}, {"from": "V", "to": "Uber", "type": "WORKS_WITH", "context": "Key customer of V"}, {"from": "V", "to": "Aviato's data quality", "type": "BELIEVES", "context": "V believes in superior data quality"}, {"from": "V", "to": "PitchBook", "type": "RELATED_TO", "context": "V aims to replace PitchBook"}]}