{"entities": [{"name": "Vrijen", "type": "PERSON", "context": "Primary user whose distinctive phrases are extracted for voice authenticity in emails"}, {"name": "Metaprompter v6", "type": "TOOL", "context": "Core framework with visible-state headers, router alignment, and nuance loader for email generation"}, {"name": "MasterVoiceSchema", "type": "TOOL", "context": "Voice fidelity schema (version \u2265 1.2) used to mirror distinctive diction"}, {"name": "Audit-First Structuring", "type": "CONCEPT", "context": "Principle requiring building maps (Missing-Content, Resonance Pool, Link Map, SpeakerQuoteMap) before drafting"}, {"name": "Socratic Expansion Layer", "type": "CONCEPT", "context": "Method that pauses for confirmation and refinements with iterative loop support"}, {"name": "Voice Fidelity", "type": "CONCEPT", "context": "Principle ensuring authentic voice through MasterVoiceSchema and transcript echoing"}, {"name": "Transcript Language Echoing", "type": "CONCEPT", "context": "Technique extracting Vrijen's distinctive phrases (confidence \u2265 0.75) for email authenticity"}, {"name": "Confidence-Based Link Insertion", "type": "CONCEPT", "context": "Method auto-inserting links only when confidence \u2265 0.75, marking uncertain as [[MISSING]]"}, {"name": "Readability Guardrails", "type": "CONCEPT", "context": "Constraints enforcing Flesch-Kincaid \u2264 10, sentence length 16-22 words, max 4 sentences per paragraph"}, {"name": "Enhanced Dial Mapping", "type": "CONCEPT", "context": "Technique calculating warmthScore and familiarityScore for tone calibration"}, {"name": "Map-Archive Integration", "type": "TOOL", "context": "System for auto-pushing distilled insights after approval"}, {"name": "Delay-Sensitivity", "type": "CONCEPT", "context": "Feature auto-detecting elapsed days since meeting, prepending apology if > 2 days"}, {"name": "Fail-Safe Drafting", "type": "CONCEPT", "context": "Principle preventing email composition until user approves maps and dials"}, {"name": "Missing-Content Map", "type": "TOOL", "context": "Audit artifact built before drafting to identify gaps"}, {"name": "Resonance Pool", "type": "TOOL", "context": "Audit artifact collecting resonant content before drafting"}, {"name": "SpeakerQuoteMap", "type": "TOOL", "context": "Audit artifact for speaker-aware parsing with quote attribution"}, {"name": "dialInferenceReport", "type": "TOOL", "context": "Report where readability violations are flagged"}, {"name": "Flesch-Kincaid", "type": "TOOL", "context": "Readability metric with target score \u2264 10"}], "relationships": [{"from": "Vrijen", "to": "Metaprompter v6", "type": "USES", "context": "Vrijen uses Metaprompter v6 for follow-up email generation"}, {"from": "Metaprompter v6", "to": "Audit-First Structuring", "type": "RELATED_TO", "context": "Core principle requiring map generation before drafting"}, {"from": "Metaprompter v6", "to": "Socratic Expansion Layer", "type": "RELATED_TO", "context": "Built-in iterative confirmation and refinement support"}, {"from": "Voice Fidelity", "to": "MasterVoiceSchema", "type": "USES", "context": "Voice fidelity achieved through MasterVoiceSchema \u2265 1.2"}, {"from": "Voice Fidelity", "to": "Transcript Language Echoing", "type": "USES", "context": "Authenticity enhanced by echoing Vrijen's distinctive phrases"}, {"from": "Transcript Language Echoing", "to": "Vrijen", "type": "RELATED_TO", "context": "Extracts Vrijen's phrases with confidence \u2265 0.75"}, {"from": "Readability Guardrails", "to": "Flesch-Kincaid", "type": "USES", "context": "Enforces Flesch-Kincaid score \u2264 10"}, {"from": "Readability Guardrails", "to": "dialInferenceReport", "type": "RELATED_TO", "context": "Violations flagged in dialInferenceReport"}, {"from": "Enhanced Dial Mapping", "to": "Voice Fidelity", "type": "RELATED_TO", "context": "Dial mapping calibrates tone through warmth and familiarity scores"}, {"from": "Audit-First Structuring", "to": "Missing-Content Map", "type": "USES", "context": "Missing-Content Map is required audit artifact"}, {"from": "Audit-First Structuring", "to": "Resonance Pool", "type": "USES", "context": "Resonance Pool is required audit artifact"}, {"from": "Audit-First Structuring", "to": "SpeakerQuoteMap", "type": "USES", "context": "SpeakerQuoteMap is required audit artifact"}, {"from": "Fail-Safe Drafting", "to": "Audit-First Structuring", "type": "RELATED_TO", "context": "Drafting blocked until maps and dials are approved"}, {"from": "Map-Archive Integration", "to": "Audit-First Structuring", "type": "RELATED_TO", "context": "Distilled insights from maps auto-pushed after approval"}]}