{"entities": [{"name": "Vrijen Attawar", "type": "PERSON", "context": "Founder of Careerspan, articulates the community flywheel strategy"}, {"name": "Logan", "type": "PERSON", "context": "Associated with Superposition, creates TikTok content, involved in GTM sync"}, {"name": "Careerspan", "type": "ORG", "context": "V's company offering reflection-first intake for founders"}, {"name": "Superposition", "type": "ORG", "context": "Recruiting execution partner that Careerspan hands off to"}, {"name": "Teal", "type": "ORG", "context": "Company whose CEO discovered Logan's TikTok and scheduled a call"}, {"name": "Community Flywheel", "type": "CONCEPT", "context": "Strategy: trusted communities attract founders \u2192 Careerspan reflection intake \u2192 Superposition execution"}, {"name": "Reflection-First Intake", "type": "CONCEPT", "context": "Careerspan's intake methodology emphasizing reflection before recruiting"}, {"name": "Composite Solution", "type": "CONCEPT", "context": "Framing Careerspan + Superposition as a unified offering rather than separate services"}, {"name": "Job Board", "type": "TOOL", "context": "Platform reaching good-enough state, triggering shift to outward storytelling"}, {"name": "TikTok", "type": "TOOL", "context": "Content platform where Logan publishes, attracted Teal CEO's attention"}, {"name": "GTM Sync 2025-12-05", "type": "EVENT", "context": "Careerspan \u00d7 Superposition go-to-market strategy meeting"}, {"name": "Teal CEO Outreach", "type": "EVENT", "context": "Teal's CEO discovered Logan's TikTok and scheduled a one-hour call"}, {"name": "Job Board Launch Decision", "type": "EVENT", "context": "Agreement for V and Logan to begin posting, shifting from setup to demand generation"}], "relationships": [{"from": "Vrijen Attawar", "to": "Careerspan", "type": "WORKS_WITH", "context": "Founder of Careerspan"}, {"from": "Logan", "to": "Superposition", "type": "WORKS_WITH", "context": "Involved with Superposition recruiting execution"}, {"from": "Vrijen Attawar", "to": "Logan", "type": "WORKS_WITH", "context": "Collaborating on GTM strategy and job board publishing"}, {"from": "Careerspan", "to": "Superposition", "type": "RELATED_TO", "context": "Careerspan hands off to Superposition for recruiting execution as composite solution"}, {"from": "Vrijen Attawar", "to": "Community Flywheel", "type": "BELIEVES", "context": "Articulated the flywheel: communities \u2192 reflection intake \u2192 recruiting execution"}, {"from": "Careerspan", "to": "Reflection-First Intake", "type": "USES", "context": "Core intake methodology for founders"}, {"from": "Community Flywheel", "to": "Composite Solution", "type": "RELATED_TO", "context": "Flywheel reframes partnership as a composite solution"}, {"from": "Logan", "to": "TikTok", "type": "USES", "context": "Creates content that attracted Teal CEO attention"}, {"from": "Teal", "to": "Teal CEO Outreach", "type": "RELATED_TO", "context": "Teal CEO initiated contact after discovering Logan's content"}, {"from": "Teal CEO Outreach", "to": "Careerspan", "type": "RELATED_TO", "context": "Raises ceiling on Careerspan's distribution and partnership landscape"}, {"from": "Job Board", "to": "Job Board Launch Decision", "type": "RELATED_TO", "context": "Board reaching good-enough state triggered decision to publish"}, {"from": "Vrijen Attawar", "to": "Job Board", "type": "USES", "context": "Will begin posting to job board for demand generation"}, {"from": "Logan", "to": "Job Board", "type": "USES", "context": "Will begin posting to job board for demand generation"}]}