{"entities": [{"name": "V", "type": "PERSON", "context": "individual related to the knowledge system"}, {"name": "reflection_classifier.py", "type": "TOOL", "context": "tool for classifying reflections"}, {"name": "reflection_block_generator.py", "type": "TOOL", "context": "tool for generating reflection blocks"}, {"name": "reflection_synthesizer_v2.py", "type": "TOOL", "context": "tool for synthesizing reflections"}, {"name": "reflection_block_suggester.py", "type": "TOOL", "context": "tool for suggesting new blocks"}, {"name": "reflection_orchestrator.py", "type": "TOOL", "context": "tool for orchestrating reflection processes"}], "relationships": [{"from": "V", "to": "reflection_classifier.py", "type": "USES", "context": "V uses this tool to classify reflections"}, {"from": "V", "to": "reflection_block_generator.py", "type": "USES", "context": "V uses this tool to generate reflection blocks"}, {"from": "V", "to": "reflection_synthesizer_v2.py", "type": "USES", "context": "V uses this tool to synthesize reflections"}, {"from": "V", "to": "reflection_block_suggester.py", "type": "USES", "context": "V uses this tool to suggest new blocks"}, {"from": "V", "to": "reflection_orchestrator.py", "type": "USES", "context": "V uses this tool to orchestrate reflection processes"}]}