{"entities": [{"name": "Careerspan", "type": "ORG", "context": "An organization gaining independence from VC pressure."}, {"name": "Nira", "type": "ORG", "context": "Aiming for $20M ARR with a lean team."}, {"name": "V", "type": "PERSON", "context": "An individual involved in the transition to 'Founder/Brand as Channel'."}, {"name": "Logan", "type": "PERSON", "context": "An individual involved in the transition to 'Founder/Brand as Channel'."}], "relationships": [{"from": "V", "to": "Logan", "type": "WORKS_WITH", "context": "Together as curators and tastemakers."}, {"from": "Nira", "to": "Lean AI Startup", "type": "BELIEVES", "context": "Prioritizing product-led growth and automation."}, {"from": "Careerspan", "to": "VC path", "type": "RELATED_TO", "context": "Choosing independence from the VC path."}]}