{"entities": [{"name": "Vrijen Attawar", "type": "PERSON", "context": "Founder of Careerspan, several years into journey, raised capital, positions as peer and light mentor"}, {"name": "Celia", "type": "PERSON", "context": "Contact V recognizes as thoughtful, doing substantive work with rare confidence at her career stage"}, {"name": "Jerry", "type": "PERSON", "context": "Associated with Latte Connect, V offers intro to Celia"}, {"name": "Careerspan", "type": "ORG", "context": "AI-driven career-development and hiring platform, pivoted from B2C coaching to hiring-focused B2B2C"}, {"name": "Connections", "type": "ORG", "context": "Celia's relationship-building network, potential complementarity with Careerspan"}, {"name": "Latte Connect", "type": "ORG", "context": "Jerry's organization, potential intro target for Celia"}, {"name": "career-tech founders Slack", "type": "ORG", "context": "Peer founder network V participates in, offers Celia a place"}, {"name": "data advantage", "type": "CONCEPT", "context": "V's core belief that unique high-signal data is the only resilient advantage in career-tech market"}, {"name": "conversational self-reflection", "type": "CONCEPT", "context": "Methodology Careerspan uses to serve candidates and create defensible data assets"}, {"name": "long-term defensibility", "type": "CONCEPT", "context": "V's strategic thinking approach, prioritizes over short-term engagement metrics"}, {"name": "talent data layer", "type": "CONCEPT", "context": "New deeper data layer Careerspan is building to predict retention, fit, and long-term success"}], "relationships": [{"from": "Vrijen Attawar", "to": "Careerspan", "type": "WORKS_WITH", "context": "Founder of the company"}, {"from": "Celia", "to": "Connections", "type": "WORKS_WITH", "context": "Runs the relationship-building network"}, {"from": "Jerry", "to": "Latte Connect", "type": "WORKS_WITH", "context": "Associated with Latte Connect"}, {"from": "Vrijen Attawar", "to": "data advantage", "type": "BELIEVES", "context": "Holds clear view that only resilient advantage in market is unique data others cannot access"}, {"from": "Vrijen Attawar", "to": "long-term defensibility", "type": "BELIEVES", "context": "Thinks in terms of long-term defensibility rather than short-term engagement metrics"}, {"from": "Careerspan", "to": "conversational self-reflection", "type": "USES", "context": "Uses to both serve candidates through coaching and create defensible data assets"}, {"from": "Careerspan", "to": "talent data layer", "type": "RELATED_TO", "context": "Building new deeper data layer to better predict retention and fit"}, {"from": "Vrijen Attawar", "to": "Celia", "type": "RELATED_TO", "context": "Light mentor relationship, shares perspective on data strategy with caveats"}, {"from": "Vrijen Attawar", "to": "Jerry", "type": "KNOWS", "context": "Offers to intro Celia to Jerry at Latte Connect"}, {"from": "Careerspan", "to": "Connections", "type": "RELATED_TO", "context": "Potential complementarity between relationship-building network and depth of reflection data"}, {"from": "Vrijen Attawar", "to": "career-tech founders Slack", "type": "RELATED_TO", "context": "Offers Celia a place in the peer founder network"}]}