{"entities": [{"name": "Zo", "type": "TOOL", "context": "AI system that generates block content from prompt files"}, {"name": "B40_INTERNAL_DECISIONS", "type": "CONCEPT", "context": "Canonical block for all strategic and tactical decisions with interrelationships"}, {"name": "B41_TEAM_COORDINATION", "type": "CONCEPT", "context": "Block for action items with owners, deadlines, and decision context via references"}, {"name": "Strategic Decisions", "type": "CONCEPT", "context": "High-level decisions categorized by type with rationale and tactical links"}, {"name": "Tactical Decisions", "type": "CONCEPT", "context": "Implementation decisions that support strategic decisions"}, {"name": "Holistic Pushes", "type": "CONCEPT", "context": "Strategic initiatives that capture both the WHY and tactical execution path"}, {"name": "Block System", "type": "TOOL", "context": "Documentation framework using numbered blocks (B##) with defined purposes and structures"}, {"name": "Prompt Files", "type": "TOOL", "context": "Input files used by Zo to generate block content"}], "relationships": [{"from": "Zo", "to": "Prompt Files", "type": "USES", "context": "Zo generates block content from prompt files"}, {"from": "Zo", "to": "Block System", "type": "USES", "context": "Zo outputs content to B##_BLOCKNAME.md files"}, {"from": "B40_INTERNAL_DECISIONS", "to": "Strategic Decisions", "type": "RELATED_TO", "context": "B40 contains strategic decisions as a core component"}, {"from": "B40_INTERNAL_DECISIONS", "to": "Tactical Decisions", "type": "RELATED_TO", "context": "B40 contains tactical decisions linked to strategic ones"}, {"from": "B40_INTERNAL_DECISIONS", "to": "Holistic Pushes", "type": "RELATED_TO", "context": "B40 captures holistic pushes as strategic initiatives"}, {"from": "Strategic Decisions", "to": "Tactical Decisions", "type": "RELATED_TO", "context": "Bidirectional interrelationships between strategic and tactical decisions"}, {"from": "B41_TEAM_COORDINATION", "to": "B40_INTERNAL_DECISIONS", "type": "RELATED_TO", "context": "B41 references B40 for decision context on action items"}, {"from": "Holistic Pushes", "to": "Strategic Decisions", "type": "RELATED_TO", "context": "Holistic pushes capture the strategic WHY"}, {"from": "Holistic Pushes", "to": "Tactical Decisions", "type": "RELATED_TO", "context": "Holistic pushes include the tactical HOW"}]}