{"entities": [{"name": "Shell", "type": "TOOL", "context": "Unix tool for calling and simple glue"}, {"name": "Python", "type": "TOOL", "context": "Used for complex logic and data processing"}, {"name": "Node.js", "type": "TOOL", "context": "API-heavy with first-class SDK"}, {"name": "Go", "type": "TOOL", "context": "Performance-critical programming language"}], "relationships": [{"from": "V", "to": "Shell", "type": "USES", "context": "V uses Shell for calling Unix tools"}, {"from": "V", "to": "Python", "type": "USES", "context": "V uses Python as the default choice for complex logic"}, {"from": "V", "to": "Node.js", "type": "USES", "context": "V uses Node.js for API-heavy applications"}, {"from": "V", "to": "Go", "type": "USES", "context": "V uses Go for performance-critical tasks if validated need exists"}]}