{"entities": [{"name": "V", "type": "PERSON", "context": "Vrijen, founder of Careerspan, main subject of the document"}, {"name": "Ilsa", "type": "PERSON", "context": "Team member in the new lean structure"}, {"name": "Logan", "type": "PERSON", "context": "Team member in the new lean structure"}, {"name": "Brady", "type": "PERSON", "context": "Teammate being actively supported into new roles"}, {"name": "Rochelle", "type": "PERSON", "context": "Teammate being actively supported into new roles"}, {"name": "Megan", "type": "PERSON", "context": "Collaborator responding with empathy, expresses desire to work together again"}, {"name": "Lean structure", "type": "CONCEPT", "context": "New organizational approach with just V, Ilsa, and Logan"}, {"name": "Hibernation mode", "type": "CONCEPT", "context": "Strategy of operating minimally while selling the company"}, {"name": "Exit", "type": "CONCEPT", "context": "Pivot toward selling the company after three years of fundraising"}, {"name": "Fundraising", "type": "CONCEPT", "context": "Three intense years that left the team exhausted"}, {"name": "Values-driven effort", "type": "CONCEPT", "context": "Active approach to supporting teammates into new roles"}, {"name": "Startup life", "type": "CONCEPT", "context": "Context framing the change as natural part of startup experience"}], "relationships": [{"from": "V", "to": "Ilsa", "type": "WORKS_WITH", "context": "Part of new lean structure team"}, {"from": "V", "to": "Logan", "type": "WORKS_WITH", "context": "Part of new lean structure team"}, {"from": "V", "to": "Brady", "type": "WORKS_WITH", "context": "Teammate being supported into new roles"}, {"from": "V", "to": "Rochelle", "type": "WORKS_WITH", "context": "Teammate being supported into new roles"}, {"from": "V", "to": "Megan", "type": "KNOWS", "context": "Collaborator with positive working relationship"}, {"from": "V", "to": "Megan", "type": "WORKS_WITH", "context": "Express desire to collaborate again on next chapter"}, {"from": "V", "to": "Lean structure", "type": "USES", "context": "Implementing as new organizational approach"}, {"from": "V", "to": "Hibernation mode", "type": "USES", "context": "Operating strategy while pursuing sale"}, {"from": "V", "to": "Exit", "type": "RELATED_TO", "context": "Pivoting toward selling the company by March"}, {"from": "Fundraising", "to": "Exit", "type": "RELATED_TO", "context": "Three intense years led to exhaustion and pivot decision"}, {"from": "V", "to": "Values-driven effort", "type": "BELIEVES", "context": "Actively supporting teammates reflects this value"}]}